{
    "Accounting and Management Information Systems Department": {
        "Chemistry Department": 1,
        "Dammam Community College": 3,
        "Electrical Engineering Department": 2,
        "Management and Marketing Department": 2,
        "Mechanical Engineering Department": 1
    },
    "Aerospace Engineering Department": {
        "Carbon Capture and Sequestration Research Center": 3,
        "Chemistry Department": 1,
        "Civil and Environmental Engineering Department": 1,
        "Civil Engineering Department": 1,
        "Environment and Water Research Center": 1,
        "Management and Marketing Department": 2,
        "Mechanical Engineering Department": 9,
        "Nanotechnology Research Excellence Center": 1,
        "Petroleum Engineering Department": 1
    },
    "Architectural Engineering Department": {
        "Architecture Department": 1,
        "Chemistry Department": 1,
        "City and Regional Planning Department": 4,
        "Civil and Environmental Engineering Department": 1,
        "Construction Engineering and Management Department": 11,
        "Dammam Community College": 12,
        "Engineering Research Center": 1,
        "Management and Marketing Department": 11,
        "Mechanical Engineering Department": 1,
        "Nanotechnology Research Excellence Center": 1
    },
    "Architecture Department": {
        "Architectural Engineering Department": 1,
        "Civil and Environmental Engineering Department": 2
    },
    "Carbon Capture and Sequestration Research Center": {
        "Aerospace Engineering Department": 3,
        "Chemical Engineering Department": 3,
        "Chemistry Department": 4,
        "Energy Efficiency Research Excellence Center": 1,
        "Engineering Research Center": 1,
        "Integrative Petroleum Research Center": 2,
        "Mechanical Engineering Department": 10,
        "Nanotechnology Research Excellence Center": 7,
        "Physics Department": 1,
        "Renewable Energy Research Excellence Center": 1
    },
    "Chemical Engineering Department": {
        "Carbon Capture and Sequestration Research Center": 3,
        "Chemistry Department": 33,
        "Civil and Environmental Engineering Department": 5,
        "Corrosion Research Excellence Center": 2,
        "Electrical Engineering Department": 7,
        "Engineering Research Center": 6,
        "Environment and Water Research Center": 7,
        "Geosciences Department": 5,
        "Hafr Al-Batin Community College": 1,
        "Integrative Petroleum Research Center": 8,
        "Life Sciences Department": 2,
        "Mathematics and Statistics Department": 1,
        "Mechanical Engineering Department": 10,
        "Nanotechnology Research Excellence Center": 107,
        "Petroleum Engineering Department": 9,
        "Physics Department": 4,
        "Projects Department": 1,
        "Refining & Petrochemicals Research Excellence Center": 2,
        "Refining and Petrochemicals Research Excellence Center": 26,
        "Renewable Energy Research Excellence Center": 10
    },
    "Chemistry Department": {
        "Accounting and Management Information Systems Department": 1,
        "Aerospace Engineering Department": 1,
        "Architectural Engineering Department": 1,
        "Carbon Capture and Sequestration Research Center": 4,
        "Chemical Engineering Department": 33,
        "Civil and Environmental Engineering Department": 17,
        "Corrosion Research Excellence Center": 32,
        "Dammam Community College": 1,
        "Electrical Engineering Department": 8,
        "Energy Efficiency Research Excellence Center": 1,
        "Energy Research and Innovation Center": 5,
        "Engineering Research Center": 9,
        "Environment & Water Research Center": 1,
        "Environment and Water Research Center": 30,
        "Geosciences Department": 13,
        "Hafr Al-Batin Community College": 1,
        "Information and Computer Science Department": 6,
        "Information System & Operations Management Department": 2,
        "Integrative Petroleum Research Center": 15,
        "Life Sciences Department": 5,
        "Mathematics and Statistics Department": 1,
        "Mechanical Engineering Department": 22,
        "Nanotechnology Research Excellence Center": 94,
        "Petroleum Engineering Department": 2,
        "Physics Department": 20,
        "Refining and Petrochemicals Research Excellence Center": 9,
        "Renewable Energy Research Excellence Center": 28
    },
    "City and Regional Planning Department": {
        "Architectural Engineering Department": 4,
        "Civil and Environmental Engineering Department": 5,
        "Construction Engineering and Management Department": 1,
        "Management and Marketing Department": 2
    },
    "Civil and Environmental Engineering Department": {
        "Aerospace Engineering Department": 1,
        "Architectural Engineering Department": 1,
        "Architecture Department": 2,
        "Chemical Engineering Department": 5,
        "Chemistry Department": 17,
        "City and Regional Planning Department": 5,
        "Computer Engineering Department": 1,
        "Corrosion Research Excellence Center": 5,
        "Electrical Engineering Department": 7,
        "Engineering Research Center": 32,
        "Environment and Water Research Center": 3,
        "Geosciences Department": 2,
        "Integrative Petroleum Research Center": 2,
        "Life Sciences Department": 1,
        "Mechanical Engineering Department": 1,
        "Nanotechnology Research Excellence Center": 13,
        "Physics Department": 5,
        "Projects Department": 1,
        "Renewable Energy Research Excellence Center": 8
    },
    "Civil Engineering Department": {
        "Aerospace Engineering Department": 1
    },
    "Computer Engineering Department": {
        "Civil and Environmental Engineering Department": 1,
        "Electrical Engineering Department": 6,
        "Engineering Research Center": 2,
        "Information and Communication Technology Center": 18,
        "Information and Computer Science Department": 4,
        "Mathematics and Statistics Department": 2,
        "Mechanical Engineering Department": 1,
        "Modeling and Computer Simulation Research Center": 1,
        "Petroleum Engineering Department": 2,
        "Renewable Energy Research Excellence Center": 3,
        "Systems Engineering Department": 8
    },
    "Construction Engineering and Management Department": {
        "Architectural Engineering Department": 11,
        "City and Regional Planning Department": 1,
        "Dammam Community College": 1,
        "Electrical Engineering Department": 1,
        "Management and Marketing Department": 8,
        "Systems Engineering Department": 4
    },
    "Corrosion Research Excellence Center": {
        "Chemical Engineering Department": 2,
        "Chemistry Department": 32,
        "Civil and Environmental Engineering Department": 5,
        "Engineering Research Center": 11,
        "Environment and Water Research Center": 1,
        "Life Sciences Department": 5,
        "Mechanical Engineering Department": 50,
        "Nanotechnology Research Excellence Center": 10,
        "Petroleum Engineering Department": 3,
        "Renewable Energy Research Excellence Center": 10
    },
    "Dammam Community College": {
        "Accounting and Management Information Systems Department": 3,
        "Architectural Engineering Department": 12,
        "Chemistry Department": 1,
        "Construction Engineering and Management Department": 1,
        "Management and Marketing Department": 3,
        "Physics Department": 1
    },
    "Electrical Engineering Department": {
        "Accounting and Management Information Systems Department": 2,
        "Chemical Engineering Department": 7,
        "Chemistry Department": 8,
        "Civil and Environmental Engineering Department": 7,
        "Computer Engineering Department": 6,
        "Construction Engineering and Management Department": 1,
        "Energy Efficiency Research Excellence Center": 3,
        "Energy Research and Innovation Center": 2,
        "Engineering Research Center": 15,
        "Environment and Water Research Center": 1,
        "Geosciences Department": 4,
        "Information and Communication Technology Center": 1,
        "Information and Computer Science Department": 5,
        "Integrative Petroleum Research Center": 1,
        "Management and Marketing Department": 1,
        "Mathematics and Statistics Department": 4,
        "Mechanical Engineering Department": 17,
        "Nanotechnology Research Excellence Center": 4,
        "Petroleum Engineering Department": 2,
        "Renewable Energy Research Excellence Center": 10,
        "Systems Engineering Department": 2
    },
    "Energy Efficiency Research Excellence Center": {
        "Carbon Capture and Sequestration Research Center": 1,
        "Chemistry Department": 1,
        "Electrical Engineering Department": 3,
        "Integrative Petroleum Research Center": 2,
        "Mechanical Engineering Department": 9,
        "Petroleum Engineering Department": 2,
        "Physics Department": 1,
        "Renewable Energy Research Excellence Center": 7
    },
    "Energy Research and Innovation Center": {
        "Chemistry Department": 5,
        "Electrical Engineering Department": 2,
        "Environment and Water Research Center": 2,
        "Integrative Petroleum Research Center": 1,
        "Mechanical Engineering Department": 9,
        "Nanotechnology Research Excellence Center": 11,
        "Petroleum Engineering Department": 1,
        "Physics Department": 13,
        "Renewable Energy Research Excellence Center": 5
    },
    "Engineering Research Center": {
        "Architectural Engineering Department": 1,
        "Carbon Capture and Sequestration Research Center": 1,
        "Chemical Engineering Department": 6,
        "Chemistry Department": 9,
        "Civil and Environmental Engineering Department": 32,
        "Computer Engineering Department": 2,
        "Corrosion Research Excellence Center": 11,
        "Electrical Engineering Department": 15,
        "Environment and Water Research Center": 3,
        "Geosciences Department": 1,
        "Information and Computer Science Department": 1,
        "Integrative Petroleum Research Center": 2,
        "Life Sciences Department": 1,
        "Mathematics and Statistics Department": 1,
        "Mechanical Engineering Department": 10,
        "Nanotechnology Research Excellence Center": 18,
        "Physics Department": 2,
        "Projects Department": 2,
        "Renewable Energy Research Excellence Center": 5,
        "Systems Engineering Department": 1
    },
    "Engn Technol Program": {
        "Mechanical Engineering Department": 3
    },
    "Environment & Water Research Center": {
        "Chemistry Department": 1,
        "Environment and Water Research Center": 7,
        "Geosciences Department": 2,
        "Life Sciences Department": 1,
        "Mechanical Engineering Department": 1
    },
    "Environment and Water Research Center": {
        "Aerospace Engineering Department": 1,
        "Chemical Engineering Department": 7,
        "Chemistry Department": 30,
        "Civil and Environmental Engineering Department": 3,
        "Corrosion Research Excellence Center": 1,
        "Electrical Engineering Department": 1,
        "Energy Research and Innovation Center": 2,
        "Engineering Research Center": 3,
        "Environment & Water Research Center": 7,
        "Geosciences Department": 22,
        "Hafr Al-Batin Community College": 1,
        "Integrative Petroleum Research Center": 8,
        "Life Sciences Department": 6,
        "Mathematics and Statistics Department": 1,
        "Mechanical Engineering Department": 20,
        "Nanotechnology Research Excellence Center": 27,
        "Petroleum Engineering Department": 3,
        "Physics Department": 19,
        "Projects Department": 1,
        "Refining and Petrochemicals Research Excellence Center": 2,
        "Renewable Energy Research Excellence Center": 20,
        "Science Research Excellence Center MIT Collaboration": 1
    },
    "General Studies Department": {
        "Global and Social Studies Department": 1
    },
    "Geosciences Department": {
        "Chemical Engineering Department": 5,
        "Chemistry Department": 13,
        "Civil and Environmental Engineering Department": 2,
        "Electrical Engineering Department": 4,
        "Engineering Research Center": 1,
        "Environment & Water Research Center": 2,
        "Environment and Water Research Center": 22,
        "Hafr Al-Batin Community College": 1,
        "Information and Computer Science Department": 5,
        "Information System & Operations Management Department": 1,
        "Integrative Petroleum Research Center": 13,
        "Life Sciences Department": 5,
        "Mathematics and Statistics Department": 1,
        "Mechanical Engineering Department": 10,
        "Nanotechnology Research Excellence Center": 2,
        "Petroleum Engineering Department": 8,
        "Physics Department": 5,
        "Projects Department": 1,
        "Renewable Energy Research Excellence Center": 1,
        "Systems Engineering Department": 1
    },
    "Global and Social Studies Department": {
        "General Studies Department": 1
    },
    "Graduate Studies": {
        "Information and Computer Science Department": 2,
        "Physics Department": 1
    },
    "Hafr Al-Batin Community College": {
        "Chemical Engineering Department": 1,
        "Chemistry Department": 1,
        "Environment and Water Research Center": 1,
        "Geosciences Department": 1,
        "Nanotechnology Research Excellence Center": 1
    },
    "Information and Communication Technology Center": {
        "Computer Engineering Department": 18,
        "Electrical Engineering Department": 1,
        "Mechanical Engineering Department": 1,
        "Modeling and Computer Simulation Research Center": 14
    },
    "Information and Computer Science Department": {
        "Chemistry Department": 6,
        "Computer Engineering Department": 4,
        "Electrical Engineering Department": 5,
        "Engineering Research Center": 1,
        "Geosciences Department": 5,
        "Graduate Studies": 2,
        "Information System & Operations Management Department": 1,
        "Mathematics and Statistics Department": 1,
        "Mechanical Engineering Department": 1,
        "Petroleum Engineering Department": 1,
        "Physics Department": 4,
        "Systems Engineering Department": 1
    },
    "Information System & Operations Management Department": {
        "Chemistry Department": 2,
        "Geosciences Department": 1,
        "Information and Computer Science Department": 1,
        "Mechanical Engineering Department": 1,
        "Systems Engineering Department": 1
    },
    "Integrative Petroleum Research Center": {
        "Carbon Capture and Sequestration Research Center": 2,
        "Chemical Engineering Department": 8,
        "Chemistry Department": 15,
        "Civil and Environmental Engineering Department": 2,
        "Electrical Engineering Department": 1,
        "Energy Efficiency Research Excellence Center": 2,
        "Energy Research and Innovation Center": 1,
        "Engineering Research Center": 2,
        "Environment and Water Research Center": 8,
        "Geosciences Department": 13,
        "Mechanical Engineering Department": 6,
        "Nanotechnology Research Excellence Center": 12,
        "Petroleum Engineering Department": 65,
        "Physics Department": 4,
        "Projects Department": 1,
        "Refining and Petrochemicals Research Excellence Center": 1,
        "Renewable Energy Research Excellence Center": 5
    },
    "Life Sciences Department": {
        "Chemical Engineering Department": 2,
        "Chemistry Department": 5,
        "Civil and Environmental Engineering Department": 1,
        "Corrosion Research Excellence Center": 5,
        "Engineering Research Center": 1,
        "Environment & Water Research Center": 1,
        "Environment and Water Research Center": 6,
        "Geosciences Department": 5,
        "Mathematics and Statistics Department": 2,
        "Mechanical Engineering Department": 3,
        "Nanotechnology Research Excellence Center": 4,
        "Petroleum Engineering Department": 1,
        "Physics Department": 2,
        "Renewable Energy Research Excellence Center": 1
    },
    "Management and Marketing Department": {
        "Accounting and Management Information Systems Department": 2,
        "Aerospace Engineering Department": 2,
        "Architectural Engineering Department": 11,
        "City and Regional Planning Department": 2,
        "Construction Engineering and Management Department": 8,
        "Dammam Community College": 3,
        "Electrical Engineering Department": 1,
        "Mathematics and Statistics Department": 1,
        "Petroleum Engineering Department": 1
    },
    "Mathematics and Statistics Department": {
        "Chemical Engineering Department": 1,
        "Chemistry Department": 1,
        "Computer Engineering Department": 2,
        "Electrical Engineering Department": 4,
        "Engineering Research Center": 1,
        "Environment and Water Research Center": 1,
        "Geosciences Department": 1,
        "Information and Computer Science Department": 1,
        "Life Sciences Department": 2,
        "Management and Marketing Department": 1,
        "Mechanical Engineering Department": 8,
        "Petroleum Engineering Department": 2,
        "Physics Department": 1,
        "Preparatory Year Program": 10,
        "Systems Engineering Department": 2
    },
    "Mechanical Engineering Department": {
        "Accounting and Management Information Systems Department": 1,
        "Aerospace Engineering Department": 9,
        "Architectural Engineering Department": 1,
        "Carbon Capture and Sequestration Research Center": 10,
        "Chemical Engineering Department": 10,
        "Chemistry Department": 22,
        "Civil and Environmental Engineering Department": 1,
        "Computer Engineering Department": 1,
        "Corrosion Research Excellence Center": 50,
        "Electrical Engineering Department": 17,
        "Energy Efficiency Research Excellence Center": 9,
        "Energy Research and Innovation Center": 9,
        "Engineering Research Center": 10,
        "Engn Technol Program": 3,
        "Environment & Water Research Center": 1,
        "Environment and Water Research Center": 20,
        "Geosciences Department": 10,
        "Information and Communication Technology Center": 1,
        "Information and Computer Science Department": 1,
        "Information System & Operations Management Department": 1,
        "Integrative Petroleum Research Center": 6,
        "Life Sciences Department": 3,
        "Mathematics and Statistics Department": 8,
        "Nanotechnology Research Excellence Center": 36,
        "Petroleum Engineering Department": 14,
        "Physics Department": 14,
        "Refining and Petrochemicals Research Excellence Center": 5,
        "Renewable Energy Research Excellence Center": 73,
        "Science Research Excellence Center MIT Collaboration": 2,
        "Systems Engineering Department": 2
    },
    "Modeling and Computer Simulation Research Center": {
        "Computer Engineering Department": 1,
        "Information and Communication Technology Center": 14
    },
    "Nanotechnology Research Excellence Center": {
        "Aerospace Engineering Department": 1,
        "Architectural Engineering Department": 1,
        "Carbon Capture and Sequestration Research Center": 7,
        "Chemical Engineering Department": 107,
        "Chemistry Department": 94,
        "Civil and Environmental Engineering Department": 13,
        "Corrosion Research Excellence Center": 10,
        "Electrical Engineering Department": 4,
        "Energy Research and Innovation Center": 11,
        "Engineering Research Center": 18,
        "Environment and Water Research Center": 27,
        "Geosciences Department": 2,
        "Hafr Al-Batin Community College": 1,
        "Integrative Petroleum Research Center": 12,
        "Life Sciences Department": 4,
        "Mechanical Engineering Department": 36,
        "Petroleum Engineering Department": 1,
        "Physics Department": 68,
        "Refining and Petrochemicals Research Excellence Center": 3,
        "Renewable Energy Research Excellence Center": 16,
        "Systems Engineering Department": 1
    },
    "Petroleum Engineering Department": {
        "Aerospace Engineering Department": 1,
        "Chemical Engineering Department": 9,
        "Chemistry Department": 2,
        "Computer Engineering Department": 2,
        "Corrosion Research Excellence Center": 3,
        "Electrical Engineering Department": 2,
        "Energy Efficiency Research Excellence Center": 2,
        "Energy Research and Innovation Center": 1,
        "Environment and Water Research Center": 3,
        "Geosciences Department": 8,
        "Information and Computer Science Department": 1,
        "Integrative Petroleum Research Center": 65,
        "Life Sciences Department": 1,
        "Management and Marketing Department": 1,
        "Mathematics and Statistics Department": 2,
        "Mechanical Engineering Department": 14,
        "Nanotechnology Research Excellence Center": 1,
        "Physics Department": 1,
        "Renewable Energy Research Excellence Center": 6,
        "Systems Engineering Department": 3
    },
    "Physical Education Department": {
        "Physics Department": 1
    },
    "Physics Department": {
        "Carbon Capture and Sequestration Research Center": 1,
        "Chemical Engineering Department": 4,
        "Chemistry Department": 20,
        "Civil and Environmental Engineering Department": 5,
        "Dammam Community College": 1,
        "Energy Efficiency Research Excellence Center": 1,
        "Energy Research and Innovation Center": 13,
        "Engineering Research Center": 2,
        "Environment and Water Research Center": 19,
        "Geosciences Department": 5,
        "Graduate Studies": 1,
        "Information and Computer Science Department": 4,
        "Integrative Petroleum Research Center": 4,
        "Life Sciences Department": 2,
        "Mathematics and Statistics Department": 1,
        "Mechanical Engineering Department": 14,
        "Nanotechnology Research Excellence Center": 68,
        "Petroleum Engineering Department": 1,
        "Physical Education Department": 1,
        "Renewable Energy Research Excellence Center": 13,
        "Science Research Excellence Center MIT Collaboration": 2,
        "Systems Engineering Department": 1
    },
    "Preparatory Year Program": {
        "Mathematics and Statistics Department": 10
    },
    "Projects Department": {
        "Chemical Engineering Department": 1,
        "Civil and Environmental Engineering Department": 1,
        "Engineering Research Center": 2,
        "Environment and Water Research Center": 1,
        "Geosciences Department": 1,
        "Integrative Petroleum Research Center": 1
    },
    "Refining & Petrochemicals Research Excellence Center": {
        "Chemical Engineering Department": 2,
        "Refining and Petrochemicals Research Excellence Center": 2
    },
    "Refining and Petrochemicals Research Excellence Center": {
        "Chemical Engineering Department": 26,
        "Chemistry Department": 9,
        "Environment and Water Research Center": 2,
        "Integrative Petroleum Research Center": 1,
        "Mechanical Engineering Department": 5,
        "Nanotechnology Research Excellence Center": 3,
        "Refining & Petrochemicals Research Excellence Center": 2,
        "Renewable Energy Research Excellence Center": 4
    },
    "Renewable Energy Research Excellence Center": {
        "Carbon Capture and Sequestration Research Center": 1,
        "Chemical Engineering Department": 10,
        "Chemistry Department": 28,
        "Civil and Environmental Engineering Department": 8,
        "Computer Engineering Department": 3,
        "Corrosion Research Excellence Center": 10,
        "Electrical Engineering Department": 10,
        "Energy Efficiency Research Excellence Center": 7,
        "Energy Research and Innovation Center": 5,
        "Engineering Research Center": 5,
        "Environment and Water Research Center": 20,
        "Geosciences Department": 1,
        "Integrative Petroleum Research Center": 5,
        "Life Sciences Department": 1,
        "Mechanical Engineering Department": 73,
        "Nanotechnology Research Excellence Center": 16,
        "Petroleum Engineering Department": 6,
        "Physics Department": 13,
        "Refining and Petrochemicals Research Excellence Center": 4
    },
    "Science Research Excellence Center MIT Collaboration": {
        "Environment and Water Research Center": 1,
        "Mechanical Engineering Department": 2,
        "Physics Department": 2
    },
    "Systems Engineering Department": {
        "Computer Engineering Department": 8,
        "Construction Engineering and Management Department": 4,
        "Electrical Engineering Department": 2,
        "Engineering Research Center": 1,
        "Geosciences Department": 1,
        "Information and Computer Science Department": 1,
        "Information System & Operations Management Department": 1,
        "Mathematics and Statistics Department": 2,
        "Mechanical Engineering Department": 2,
        "Nanotechnology Research Excellence Center": 1,
        "Petroleum Engineering Department": 3,
        "Physics Department": 1
    }
}